axi_led.v
module axi4_lite_slave (
    input wire clk,
    input wire rst_n,
    output wire led,

    // Write address channel
    input wire [3:0]  AWADDR,
    input wire        AWVALID,
    output reg        AWREADY,

    // Write data channel
    input wire [31:0] WDATA,
    input wire        WVALID,
    output reg        WREADY,

    // Write response
    output reg        BVALID,
    input wire        BREADY,

    // Read address
    input wire [3:0]  ARADDR,
    input wire        ARVALID,
    output reg        ARREADY,

    // Read data
    output reg [31:0] RDATA,
    output reg        RVALID,
    input wire        RREADY
);

// Registers
reg [31:0] reg0, reg1, reg2, reg3;

// LED connection
assign led = reg0[0];

// WRITE
always @(posedge clk or negedge rst_n) begin
    if (!rst_n) begin
        AWREADY <= 0; WREADY <= 0; BVALID <= 0;
        reg0 <= 0; reg1 <= 0; reg2 <= 0; reg3 <= 0;
    end else begin
        if (AWVALID && WVALID && !BVALID) begin
            AWREADY <= 1;
            WREADY  <= 1;

            case (AWADDR[3:2])
                2'b00: reg0 <= WDATA;
                2'b01: reg1 <= WDATA;
                2'b10: reg2 <= WDATA;
                2'b11: reg3 <= WDATA;
            endcase

            BVALID <= 1;
        end else begin
            AWREADY <= 0;
            WREADY  <= 0;
        end

        if (BVALID && BREADY)
            BVALID <= 0;
    end
end

// READ
always @(posedge clk or negedge rst_n) begin
    if (!rst_n) begin
        ARREADY <= 0; RVALID <= 0; RDATA <= 0;
    end else begin
        if (ARVALID && !RVALID) begin
            ARREADY <= 1;

            case (ARADDR[3:2])
                2'b00: RDATA <= reg0;
                2'b01: RDATA <= reg1;
                2'b10: RDATA <= reg2;
                2'b11: RDATA <= reg3;
            endcase

            RVALID <= 1;
        end else begin
            ARREADY <= 0;
        end

        if (RVALID && RREADY)
            RVALID <= 0;
    end
end

endmodule


// ================= TESTBENCH =================

module tb;

reg clk = 0;
always #5 clk = ~clk;

reg rst_n;

// AXI signals
reg [3:0] AWADDR;
reg AWVALID;
wire AWREADY;

reg [31:0] WDATA;
reg WVALID;
wire WREADY;

wire BVALID;
reg BREADY;

reg [3:0] ARADDR;
reg ARVALID;
wire ARREADY;

wire [31:0] RDATA;
wire RVALID;
reg RREADY;

wire led;

// DUT
axi4_lite_slave dut (
    .clk(clk), .rst_n(rst_n), .led(led),
    .AWADDR(AWADDR), .AWVALID(AWVALID), .AWREADY(AWREADY),
    .WDATA(WDATA), .WVALID(WVALID), .WREADY(WREADY),
    .BVALID(BVALID), .BREADY(BREADY),
    .ARADDR(ARADDR), .ARVALID(ARVALID), .ARREADY(ARREADY),
    .RDATA(RDATA), .RVALID(RVALID), .RREADY(RREADY)
);

initial begin
    $dumpfile("axi_led.vcd");
    $dumpvars(0, tb);

    rst_n = 0;
    AWVALID = 0; WVALID = 0; BREADY = 0;
    ARVALID = 0; RREADY = 0;

    #20 rst_n = 1;

    // LED ON
    #10;
    AWADDR = 4'h0;
    WDATA  = 32'h1;
    AWVALID = 1; WVALID = 1;
    #10 AWVALID = 0; WVALID = 0;

    BREADY = 1; #10 BREADY = 0;

    #10;
    $display("LED = %b (should be 1)", led);

    // LED OFF
    #20;
    AWADDR = 4'h0;
    WDATA  = 32'h0;
    AWVALID = 1; WVALID = 1;
    #10 AWVALID = 0; WVALID = 0;

    BREADY = 1; #10 BREADY = 0;

    #10;
    $display("LED = %b (should be 0)", led);

    #20 $finish;
end

endmodule

axi_led.vcd
$date
	Wed Mar 25 14:53:11 2026
$end
$version
	Icarus Verilog
$end
$timescale
	1s
$end
$scope module tb $end
$var wire 1 ! led $end
$var wire 1 " WREADY $end
$var wire 1 # RVALID $end
$var wire 32 $ RDATA [31:0] $end
$var wire 1 % BVALID $end
$var wire 1 & AWREADY $end
$var wire 1 ' ARREADY $end
$var reg 4 ( ARADDR [3:0] $end
$var reg 1 ) ARVALID $end
$var reg 4 * AWADDR [3:0] $end
$var reg 1 + AWVALID $end
$var reg 1 , BREADY $end
$var reg 1 - RREADY $end
$var reg 32 . WDATA [31:0] $end
$var reg 1 / WVALID $end
$var reg 1 0 clk $end
$var reg 1 1 rst_n $end
$scope module dut $end
$var wire 4 2 ARADDR [3:0] $end
$var wire 1 ) ARVALID $end
$var wire 4 3 AWADDR [3:0] $end
$var wire 1 + AWVALID $end
$var wire 1 , BREADY $end
$var wire 1 - RREADY $end
$var wire 32 4 WDATA [31:0] $end
$var wire 1 / WVALID $end
$var wire 1 0 clk $end
$var wire 1 1 rst_n $end
$var wire 1 ! led $end
$var reg 1 ' ARREADY $end
$var reg 1 & AWREADY $end
$var reg 1 % BVALID $end
$var reg 32 5 RDATA [31:0] $end
$var reg 1 # RVALID $end
$var reg 1 " WREADY $end
$var reg 32 6 reg0 [31:0] $end
$var reg 32 7 reg1 [31:0] $end
$var reg 32 8 reg2 [31:0] $end
$var reg 32 9 reg3 [31:0] $end
$upscope $end
$upscope $end
$enddefinitions $end
$comment Show the parameter values. $end
$dumpall
$end
#0
$dumpvars
b0 9
b0 8
b0 7
b0 6
b0 5
bx 4
bx 3
bx 2
01
00
0/
bx .
0-
0,
0+
bx *
0)
bx (
0'
0&
0%
b0 $
0#
0"
0!
$end
#5
10
#10
00
#15
10
#20
00
11
#25
10
#30
00
1/
1+
b1 .
b1 4
b0 *
b0 3
#35
1!
1%
b1 6
1"
1&
10
#40
00
1,
0/
0+
#45
0%
0"
0&
10
#50
00
0,
#55
10
#60
00
#65
10
#70
00
#75
10
#80
00
1/
1+
b0 .
b0 4
#85
0!
1%
b0 6
1"
1&
10
#90
00
1,
0/
0+
#95
0%
0"
0&
10
#100
00
0,
